.DS_Store
cdascorer/Old_GUI.py
cdascorer/__init__.py
cdascorer/cdametadata.py
cdascorer/cdascorer_gui.py
cdascorer/cdascorer_gui_windows.py
cdascorer/image_colour.py
cdascorer/tkinterwindow.py
cdascorer-0.0.0.dev26.data/scripts/cdascorer
cdascorer-0.0.0.dev26.data/scripts/cdascorer-run
cdascorer-0.0.0.dev26.data/scripts/cdascorer-test
cdascorer-0.0.0.dev26.data/scripts/cdascorer-view
cdascorer-0.0.0.dev26.data/scripts/cdascorer-windows-test.py
cdascorer-0.0.0.dev26.data/scripts/cdascorer-windows.py
cdascorer-data/__init__.py
cdascorer-data/lesion_score_key.jpg
cdascorer-data/test_cda_img.jpg
cdascorer-0.0.0.dev26.dist-info/METADATA
cdascorer-0.0.0.dev26.dist-info/WHEEL
cdascorer-0.0.0.dev26.dist-info/top_level.txt
cdascorer-0.0.0.dev26.dist-info/RECORD
