Metadata-Version: 2.1
Name: cdascorer
Version: 0.0.0.dev26
Summary: Cell Death Area Data Collection
Home-page: https://github.com/joshuandwilliams/CDAScorer
Author: Joshua Williams
Author-email: <jowillia@nbi.ac.uk>
License: LICENSE.txt
Requires-Dist: pandas
Requires-Dist: natsort
Requires-Dist: importlib-resources
Requires-Dist: Pillow
